Workbook

Sheet Portada
F3: Elaboración Propuesta Fichas Tecnicas
D7: Integrantes: | F7: Maria Camila Molina Rincon
F8: Johan Esteban Casquete Reina
F9: Melany Vanneza pinzon laserna
F10: Andres Felipe Reyes Saenz
F11: Julian Arley Moreno Maldonado
D12: Roles del Spa: Administrador, Recepcionista, Empleados, Cliente
G15: Control de invetario para
G17: ADSO

Sheet Torre admin
D2: CUADRO DE COTIZACIONES
A5: Cuadro Comparativo de Cotizaciones
A7: Presupuestos (a) | B7: Empresa (Nombre fiscal de la empresa) | C7: NIT Dirección, Teléfono | D7: Descripción del bien/ servicio (b) Características de los bienes/ servicios | E7: Importe Unitario (moneda nacional) | F7: Importe Total IVA incluido (moneda nacional) | G7: Importe Total (moneda extranjera) | H7: Tipo de cambio | I7: Forma de Pago (Contado o Cheque) | J7: Observaciones (se debe incluir toda aquella característica que no ha sido posible incluir anteriormente)
A8: Nº 1 | B8: Computadores y Partes Tigertech s.a.s | C8: 901.456.832-7. Cra. 16a #78-79 of 607, Chapinero, Bogotá. 3195753830 | D8: PC GAMER AMD RYZEN 5 5600G A520M WIFI 16GB 512 M2 VEGA 7 | E8: $1.970.000 | F8: $1.970.000 | G8: $533,87 | H8: 3.690,16 | I8: Efectivo y Transferencias | J8: Precio solo Efectivo, con tarjeta el valor sube hasta un 19%
A9: Nº2 | B9: Power Deal S.A.S | C9: 900.190.657-7.Cra 15 77-05 oficina 320. 3204705000 | D9: TORRE KRAKEN R5 / ANTEC VCX30 + 5 ARGB / RYZ 5 5600G + A520M + 16GB DDR4 + 512 NVMe + 450W | E9: $2.079.000 | F9: $2.079.000 | G9: $563,40 | H9: 3.690,17 | I9: Efectivo y Tarjetas | J9: Precio Sin envios y sujeto a descuentos de la empresa
A10: Nº 3 | B10: Gtech Systems S A S | C10: 900.870.551-3. CL 47 # 13 - 15 AP 501. 3196262690 | D10: PC Monster A: Ryzen 5 5600G 8 Threads, Vega Graphics, 16GB DDR4, NVMe 512 | E10: 2017000 | F10: 2017000 | G10: $546,60 | H10: 3.690,18 | I10: Efectivo y Tarjetas | J10: Precio con tarjeta, pagos con efectivo llevan un descuento de 3%
A13: (a) Se deben presentar tres (3) presupuestos cuando: El valor del gasto supere el monto de pesos un mil ($ 1.000,00). Se pueden presentar al menos tres (3) solicitudes de cotización (del bien o servicio a contratar) cursadas a tres o más empresas oferentes. La selección del proveedor se hará con el criterio del más bajo precio. En caso de no contar con tres (3) presupuestos, o no poder seleccionar al proveedor que ofrece menor precio, presentar este cuadro una nota de justificación siguiendo las pautas del ítem (XX)
A15: (b) Ejemplos: En el caso de viajes, indicar Origen/Destino (si corresponde también escalas) Si se tratara de servicios tipo catering, indicar las cantidades de asistentes, así como los días en que se demanda la prestación del servicio. Si fuera papelería indicar, cantidades de afiches, trípticos, etc.

Sheet Monitor Admin
D2: CUADRO DE COTIZACIONES
A5: Cuadro Comparativo de Cotizaciones
A7: Presupuestos (a) | B7: Empresa (Nombre fiscal de la empresa) | C7: NIT Dirección, Teléfono | D7: Descripción del bien/ servicio (b) Características de los bienes/ servicios | E7: Importe Unitario (moneda nacional) | F7: Importe Total IVA incluido (moneda nacional) | G7: Importe Total (moneda extranjera) | H7: Tipo de cambio | I7: Forma de Pago (Contado o Cheque) | J7: Observaciones (se debe incluir toda aquella característica que no ha sido posible incluir anteriormente)
A8: Nº 1 | B8: Computadores y Partes Tigertech s.a.s | C8: 901.456.832-7. Cra. 16a #78-79 of 607, Chapinero, Bogotá. 3195753830 | D8: MONITOR ASUS 22 VP229HF 1080 100HZ FHD | E8: 330000 | F8: 330000 | G8: 89.43 | H8: 3.690,16 | I8: Efectivo y Transferencias | J8: Precio solo Efectivo, con tarjeta el valor sube hasta un 19%
A9: Nº2 | B9: Power Deal S.A.S | C9: 900.190.657-7.Cra 15 77-05 oficina 320. 3204705000 | D9: MONITOR ACER 22" EK220Q 100Hz 1Ms 1920 X 1080 VA HDMI + VGA | E9: 360000 | F9: 360000 | G9: 97.56 | H9: 3.690,17 | I9: Efectivo y Tarjetas | J9: Precio Sin envios y sujeto a descuentos de la empresa
A10: Nº 3 | B10: Gtech Systems S A S | C10: 900.870.551-3. CL 47 # 13 - 15 AP 501. 3196262690 | D10: Monitor Gamer IPS Iceberg SPECMAX 24″ 1ms 100Hz GSync FreeSync HDMI FullHD G24V3 | E10: 399900 | F10: 399900 | G10: 109.37 | H10: 3.690,18 | I10: Efectivo y Tarjetas | J10: Precio con tarjeta, pagos con efectivo llevan un descuento de 3%
A13: (a) Se deben presentar tres (3) presupuestos cuando: El valor del gasto supere el monto de pesos un mil ($ 1.000,00). Se pueden presentar al menos tres (3) solicitudes de cotización (del bien o servicio a contratar) cursadas a tres o más empresas oferentes. La selección del proveedor se hará con el criterio del más bajo precio. En caso de no contar con tres (3) presupuestos, o no poder seleccionar al proveedor que ofrece menor precio, presentar este cuadro una nota de justificación siguiendo las pautas del ítem (XX)
A15: (b) Ejemplos: En el caso de viajes, indicar Origen/Destino (si corresponde también escalas) Si se tratara de servicios tipo catering, indicar las cantidades de asistentes, así como los días en que se demanda la prestación del servicio. Si fuera papelería indicar, cantidades de afiches, trípticos, etc.

Sheet DiscoSolido Admin
D2: CUADRO DE COTIZACIONES
A5: Cuadro Comparativo de Cotizaciones
A7: Presupuestos (a) | B7: Empresa (Nombre fiscal de la empresa) | C7: NIT Dirección, Teléfono | D7: Descripción del bien/ servicio (b) Características de los bienes/ servicios | E7: Importe Unitario (moneda nacional) | F7: Importe Total IVA incluido (moneda nacional) | G7: Importe Total (moneda extranjera) | H7: Tipo de cambio | I7: Forma de Pago (Contado o Cheque) | J7: Observaciones (se debe incluir toda aquella característica que no ha sido posible incluir anteriormente)
A8: Nº 1 | B8: Todo Tintas y Suministros | C8: 830031519. CR 69 K NO. 69-35. 313 854 6796 | D8: Unidad solida M2 Xpress Legend 710 de 512 Gb Adata | E8: $ 327.000 | F8: $ 327.000 | G8: $88,62 | H8: 3.690,16 | I8: Efectivo y Tarjetas
A9: Nº2 | B9: Frontier | C9: 800015163-1. Calle 10 Sur No. 48A-55 . (4) 448 5100 | D9: Disco de Estado Sólido 2.5 512GB SATA XUE® BLINK S500/512 550MB/S | E9: $ 356,663 | F9: $ 356,663 | G9: $96,65 | H9: 3.690,17 | I9: Efectivo y Tarjetas
A10: Nº 3 | B10: SYSTORE COLOMBIA | C10: 901450245. Cr 15 # 77 05 Local 258, (314) 251 26 38 | D10: Disco Sòlido 512gb Lexar NS100 Sata3 LNS100-512RBNA | E10: 370.000 $ | F10: 370.000 $ | G10: $100,27 | H10: 3.690,18 | I10: Efectivo y Tarjetas
A13: (a) Se deben presentar tres (3) presupuestos cuando: El valor del gasto supere el monto de pesos un mil ($ 1.000,00). Se pueden presentar al menos tres (3) solicitudes de cotización (del bien o servicio a contratar) cursadas a tres o más empresas oferentes. La selección del proveedor se hará con el criterio del más bajo precio. En caso de no contar con tres (3) presupuestos, o no poder seleccionar al proveedor que ofrece menor precio, presentar este cuadro una nota de justificación siguiendo las pautas del ítem (XX)
A15: (b) Ejemplos: En el caso de viajes, indicar Origen/Destino (si corresponde también escalas) Si se tratara de servicios tipo catering, indicar las cantidades de asistentes, así como los días en que se demanda la prestación del servicio. Si fuera papelería indicar, cantidades de afiches, trípticos, etc.

Sheet Disco duro interno Admin
D2: CUADRO DE COTIZACIONES
A5: Cuadro Comparativo de Cotizaciones
A7: Presupuestos (a) | B7: Empresa (Nombre fiscal de la empresa) | C7: NIT Dirección, Teléfono | D7: Descripción del bien/ servicio (b) Características de los bienes/ servicios | E7: Importe Unitario (moneda nacional) | F7: Importe Total IVA incluido (moneda nacional) | G7: Importe Total (moneda extranjera) | H7: Tipo de cambio | I7: Forma de Pago (Contado o Cheque) | J7: Observaciones (se debe incluir toda aquella característica que no ha sido posible incluir anteriormente)
A8: Nº 1 | B8: Todo Tintas y Suministros | C8: 830031519. CR 69 K NO. 69-35. 313 854 6796 | D8: Unidad solida M2 Xpress Legend 710 de 512 Gb Adata | E8: $295.000 | F8: $295.001 | G8: $79,94 | H8: 3.690,16 | I8: Efectivo y Tarjetas
A9: Nº2 | B9: Frontier | C9: 800015163-1. Calle 10 Sur No. 48A-55 . (4) 448 5100 | D9: Disco de Estado Sólido SSD SanDisk Plus 500GB M.2 NVMe PCIe 3.0 | E9: $ 373,745 | F9: $ 373,745 | G9: $101,28 | H9: 3.690,17 | I9: Efectivo y Tarjetas
A10: Nº 3 | B10: SYSTORE COLOMBIA | C10: 901450245. Cr 15 # 77 05 Local 258, (314) 251 26 38 | D10: Disco Solido M.2 Nvme 512gb Adata Legend 700 ALEG-700-512GCS | E10: 395.000 $ | F10: 395.000 $ | G10: $107,04 | H10: 3.690,18 | I10: Efectivo y Tarjetas
A13: (a) Se deben presentar tres (3) presupuestos cuando: El valor del gasto supere el monto de pesos un mil ($ 1.000,00). Se pueden presentar al menos tres (3) solicitudes de cotización (del bien o servicio a contratar) cursadas a tres o más empresas oferentes. La selección del proveedor se hará con el criterio del más bajo precio. En caso de no contar con tres (3) presupuestos, o no poder seleccionar al proveedor que ofrece menor precio, presentar este cuadro una nota de justificación siguiendo las pautas del ítem (XX)
A15: (b) Ejemplos: En el caso de viajes, indicar Origen/Destino (si corresponde también escalas) Si se tratara de servicios tipo catering, indicar las cantidades de asistentes, así como los días en que se demanda la prestación del servicio. Si fuera papelería indicar, cantidades de afiches, trípticos, etc.

Sheet ram Admin
D2: CUADRO DE COTIZACIONES
A5: Cuadro Comparativo de Cotizaciones
A7: Presupuestos (a) | B7: Empresa (Nombre fiscal de la empresa) | C7: NIT Dirección, Teléfono | D7: Descripción del bien/ servicio (b) Características de los bienes/ servicios | E7: Importe Unitario (moneda nacional) | F7: Importe Total IVA incluido (moneda nacional) | G7: Importe Total (moneda extranjera) | H7: Tipo de cambio | I7: Forma de Pago (Contado o Cheque) | J7: Observaciones (se debe incluir toda aquella característica que no ha sido posible incluir anteriormente)
A8: Nº 1 | B8: Todo Tintas y Suministros | C8: 830031519. CR 69 K NO. 69-35. 313 854 6796 | D8: Memoria RAM ADATA 16Gb DDR4 3200 PC | E8: $ 448.000 | F8: $ 448.000 | G8: $121,41 | H8: 3.690,16 | I8: Efectivo y Tarjetas
A9: Nº2 | B9: Frontier | C9: 800015163-1. Calle 10 Sur No. 48A-55 . (4) 448 5100 | D9: Memoria Ram para PC DDR4 16GB Kingston 3200mhz | E9: $ 330,709 | F9: $ 330,709 | G9: $89,45 | H9: 3.690,17 | I9: Efectivo y Tarjetas
A10: Nº 3 | B10: SYSTORE COLOMBIA | C10: 901450245. Cr 15 # 77 05 Local 258, (314) 251 26 38 | D10: Memoria Ram Ddr4 Pc 16Gb Kingston 2666Mhz KVR26N17S8/16 | E10: 495.000 $ | F10: 495.000 $ | G10: $134,14 | H10: 3.690,18 | I10: Efectivo y Tarjetas
A13: (a) Se deben presentar tres (3) presupuestos cuando: El valor del gasto supere el monto de pesos un mil ($ 1.000,00). Se pueden presentar al menos tres (3) solicitudes de cotización (del bien o servicio a contratar) cursadas a tres o más empresas oferentes. La selección del proveedor se hará con el criterio del más bajo precio. En caso de no contar con tres (3) presupuestos, o no poder seleccionar al proveedor que ofrece menor precio, presentar este cuadro una nota de justificación siguiendo las pautas del ítem (XX)
A15: (b) Ejemplos: En el caso de viajes, indicar Origen/Destino (si corresponde también escalas) Si se tratara de servicios tipo catering, indicar las cantidades de asistentes, así como los días en que se demanda la prestación del servicio. Si fuera papelería indicar, cantidades de afiches, trípticos, etc.

Sheet Servidor Admin
D2: CUADRO DE COTIZACIONES
A5: Cuadro Comparativo de Cotizaciones
A7: Presupuestos (a) | B7: Empresa (Nombre fiscal de la empresa) | C7: NIT Dirección, Teléfono | D7: Descripción del bien/ servicio (b) Características de los bienes/ servicios | E7: Importe Unitario (moneda nacional) | F7: Importe Total IVA incluido (moneda nacional) | G7: Importe Total (moneda extranjera) | H7: Tipo de cambio | I7: Forma de Pago (Contado o Cheque) | J7: Observaciones (se debe incluir toda aquella característica que no ha sido posible incluir anteriormente)
A8: Nº 1 | B8: donweb | C8: 901292649-1 CARRERA 87 147 B 25 CA 33, 6014602708 | D8: Servicio de hosting de Paginas web | E8: $11.500 | F8: $11.500 | G8: $3,12 | H8: 3.690,16 | I8: Tarjeta | J8: 200GB de almacenamiento NVMe, Dominio .COM.CO GRATIS, Cuentas de correo ILIMITADO
A9: Nº2 | B9: HostGator | C9: No cuenta con NIT, HostGator es una sociedad privada que opera bajo las leyes de Texas | D9: Servicio de hosting de Paginas web | E9: $11.200 | F9: $11.200 | G9: $3,04 | H9: 3.690,17 | I9: Tarjeta | J9: 25 GB de almacenamiento NVMe, Agente de IA, Backup Diario, Correos ilimitados
A10: Nº 3 | B10: Hostinger | C10: No posee NIT pues no se encuentra registrada en la dian, ubicacion principal Vilnius, Lituania | D10: Servicio de hosting de Paginas web | E10: $11.900 | F10: $11.900 | G10: $3,22 | H10: 3.690,18 | I10: Tarjeta | J10: 50 GB del almacenamiento NVMe, Backups diarios, Agente de IA, permite creacion de multiples sitios web
E11: 11.9
A13: (a) Se deben presentar tres (3) presupuestos cuando: El valor del gasto supere el monto de pesos un mil ($ 1.000,00). Se pueden presentar al menos tres (3) solicitudes de cotización (del bien o servicio a contratar) cursadas a tres o más empresas oferentes. La selección del proveedor se hará con el criterio del más bajo precio. En caso de no contar con tres (3) presupuestos, o no poder seleccionar al proveedor que ofrece menor precio, presentar este cuadro una nota de justificación siguiendo las pautas del ítem (XX)
A15: (b) Ejemplos: En el caso de viajes, indicar Origen/Destino (si corresponde también escalas) Si se tratara de servicios tipo catering, indicar las cantidades de asistentes, así como los días en que se demanda la prestación del servicio. Si fuera papelería indicar, cantidades de afiches, trípticos, etc.

Sheet Teclado Admin
D2: CUADRO DE COTIZACIONES
A5: Cuadro Comparativo de Cotizaciones
A7: Presupuestos (a) | B7: Empresa (Nombre fiscal de la empresa) | C7: NIT Dirección, Teléfono | D7: Descripción del bien/ servicio (b) Características de los bienes/ servicios | E7: Importe Unitario (moneda nacional) | F7: Importe Total IVA incluido (moneda nacional) | G7: Importe Total (moneda extranjera) | H7: Tipo de cambio | I7: Forma de Pago (Contado o Cheque) | J7: Observaciones (se debe incluir toda aquella característica que no ha sido posible incluir anteriormente)
A8: Nº 1 | B8: Almacenes Éxito S.A | C8: 890.900.943-1 Cra. 68b #25B-80, Bogotá (601) 407 3033 | D8: Teclado ESENSES Alámbrico BK-108 Negro | E8: 39.900 | F8: 39.900 | G8: $10,81 | H8: 3.690,16 | I8: Efectivo(en el almacen), targeta, PSE
A9: Nº2 | B9: Colombiana de Comercio S.A | C9: 890.900.608-9 Cra. 90 #60, Bogotá (1) 745 5444 | D9: Teclado Hp 125 Alámbrico Usb Negro Español | E9: 39.900 | F9: 39.900 | G9: $10,81 | H9: 3.690,17 | I9: Efectivo(en el almacen), targeta, PSE
A10: Nº 3 | B10: CENCOSUD COLOMBIA S.A | C10: 900.155.107-1 Avenida 9 # 125-30, Bogotá, Colombia 601 348 9888 | D10: Teclado USB Jaltech forza KB 05 | E10: 39.900 | F10: 39.900 | G10: $10,81 | H10: 3.690,18 | I10: Efectivo(en el almacen), targeta, PSE
A13: (a) Se deben presentar tres (3) presupuestos cuando: El valor del gasto supere el monto de pesos un mil ($ 1.000,00). Se pueden presentar al menos tres (3) solicitudes de cotización (del bien o servicio a contratar) cursadas a tres o más empresas oferentes. La selección del proveedor se hará con el criterio del más bajo precio. En caso de no contar con tres (3) presupuestos, o no poder seleccionar al proveedor que ofrece menor precio, presentar este cuadro una nota de justificación siguiendo las pautas del ítem (XX)
A15: (b) Ejemplos: En el caso de viajes, indicar Origen/Destino (si corresponde también escalas) Si se tratara de servicios tipo catering, indicar las cantidades de asistentes, así como los días en que se demanda la prestación del servicio. Si fuera papelería indicar, cantidades de afiches, trípticos, etc.

Sheet Mouse Admin
D2: CUADRO DE COTIZACIONES
A5: Cuadro Comparativo de Cotizaciones
A7: Presupuestos (a) | B7: Empresa (Nombre fiscal de la empresa) | C7: NIT Dirección, Teléfono | D7: Descripción del bien/ servicio (b) Características de los bienes/ servicios | E7: Importe Unitario (moneda nacional) | F7: Importe Total IVA incluido (moneda nacional) | G7: Importe Total (moneda extranjera) | H7: Tipo de cambio | I7: Forma de Pago (Contado o Cheque) | J7: Observaciones (se debe incluir toda aquella característica que no ha sido posible incluir anteriormente)
A8: Nº 1 | B8: Almacenes Éxito S.A | C8: 890.900.943-1 Cra. 68b #25B-80, Bogotá (601) 407 3033 | D8: Mouse LENOVO Alámbrico Óptico 300 Negro | E8: $29.900 | F8: $29.900 | G8: $8,10 | H8: 3.690,16 | I8: Efectivo(en el almacen), targeta, PSE
A9: Nº2 | B9: Colombiana de Comercio S.A | C9: 890.900.608-9 Cra. 90 #60, Bogotá (1) 745 5444 | D9: Mouse Usb Logitech M90 Negro | E9: $ 24.900 | F9: $ 29.900 | G9: $8,10 | H9: 3.690,17 | I9: Efectivo(en el almacen), targeta, PSE
A10: Nº 3 | B10: CENCOSUD COLOMBIA S.A | C10: 900.155.107-1 Avenida 9 # 125-30, Bogotá, Colombia 601 348 9888 | D10: Mouse HP 100 alámbrico Negro | E10: $ 29.900 | F10: $ 29.900 | G10: $8,10 | H10: 3.690,18 | I10: Efectivo(en el almacen), targeta, PSE
I11: CONTADO
A13: (a) Se deben presentar tres (3) presupuestos cuando: El valor del gasto supere el monto de pesos un mil ($ 1.000,00). Se pueden presentar al menos tres (3) solicitudes de cotización (del bien o servicio a contratar) cursadas a tres o más empresas oferentes. La selección del proveedor se hará con el criterio del más bajo precio. En caso de no contar con tres (3) presupuestos, o no poder seleccionar al proveedor que ofrece menor precio, presentar este cuadro una nota de justificación siguiendo las pautas del ítem (XX)
A15: (b) Ejemplos: En el caso de viajes, indicar Origen/Destino (si corresponde también escalas) Si se tratara de servicios tipo catering, indicar las cantidades de asistentes, así como los días en que se demanda la prestación del servicio. Si fuera papelería indicar, cantidades de afiches, trípticos, etc.

Sheet Portatil Nosotros
D2: CUADRO DE COTIZACIONES
A5: Cuadro Comparativo de Cotizaciones
A7: Presupuestos (a) | B7: Empresa (Nombre fiscal de la empresa) | C7: NIT Dirección, Teléfono | D7: Descripción del bien/ servicio (b) Características de los bienes/ servicios | E7: Importe Unitario (moneda nacional) | F7: Importe Total IVA incluido (moneda nacional) | G7: Importe Total (moneda extranjera) | H7: Tipo de cambio | I7: Forma de Pago (Contado o Cheque) | J7: Observaciones (se debe incluir toda aquella característica que no ha sido posible incluir anteriormente)
A8: Nº 1 | B8: Mercado Libre | C8: 830067394-6 Carrera 17 No. 93 - 09, Bogotá D.C.MercadoLibre | D8: Portátil Hp 15-fc0272la Amd Ryzen 7 16 Gb De Ram 512 Gb Ssd https://www.mercadolibre.com.co/portatil-hp-15fc0260la-r57520u-8gb-1tb-ssd-w11/up/MCOU3414562067#polycard_client=search-desktop&search_layout=grid&position=45&type=product&tracking_id=0c1bb0a9-ac8d-43b7-8fd1-87587f3ec486&wid=MCO3120823028&sid=search | E8: 2029000 | F8: 2029000 | G8: 557.45 | H8: 3.679,25 | I8: Mercado Pago: Saldo disponible en la cuenta de Mercado Pago.Tarjetas de Débito: Visa y Mastercard. | J8: 1 año de garantía
A9: Nº2 | B9: Panamericana | C9: Panamericana Librería y Papelería S.A. (Colombia) 830037946 | D9: Portátil Acer Aspire Go de 15.6", Intel Ci5 13420H, RAM 16 GB, 512 GB SSD, W11 https://www.panamericana.com.co/portatil-acer-aspire-go-de-15-6-intel-ci5-13420h-ram-16-gb-512gb-ssd-w11-721022/p?srsltid=AfmBOorSE7BB_BCG3W_AEhEnNHiu88VyaZDwv2a78r36L-vN7R7w4uIp | E9: 2399000 | F9: 2399000 | G9: 649.65 | H9: 3.679,26 | I9: ago en una sola exhibición o PPD - Pago en parcialidades o diferido | J9: 1 año de garantía
A10: Nº 3 | B10: Mercado Libre | C10: 830067394-6 Carrera 17 No. 93 - 09, Bogotá D.C.MercadoLibre | D10: Portatil Asus Vivobook 15 Amd Ryzen 7 16gb 512gb Windows 11 Plateado https://www.mercadolibre.com.co/portatil-asus-vivobook-15-amd-ryzen-7-16gb-512gb-windows-11-plateado/p/MCO63052946?pdp_filters=item_id%3AMCO1789962793&from=gshop&matt_tool=87585337&matt_word=&matt_source=google&matt_campaign_id=22126928786&matt_ad_group_id=173140661443&matt_match_type=&matt_network=g&matt_device=c&matt_creative=729836849962&matt_keyword=&matt_ad_position=&matt_ad_type=pla&matt_merchant_id=735122983&matt_product_id=MCO63052946-product&matt_product_partition_id=2389933078058&matt_target_id=aud-2200363567910:pla-2389933078058&cq_src=google_ads&cq_cmp=22126928786&cq_net=g&cq_plt=gp&cq_med=pla&gad_source=1&gad_campaignid=22126928786&gbraid=0AAAAAD1DcozRCWvWDKp-eHmX_1NPqrQx0&gclid=Cj0KCQjws83OBhD4ARIsACblj1_bGFdwebhPcJAi9_rqQF3ZMyyWDJ6DbcuOuyAik44e8tIH7mJII14aApUrEALw_wcB | E10: 1999000 | F10: 1999000 | G10: 549.21 | H10: 3.679,27 | I10: Mercado Pago: Saldo disponible en la cuenta de Mercado Pago.Tarjetas de Débito: Visa y Mastercard. | J10: 1 año de garantía
A13: (a) Se deben presentar tres (3) presupuestos cuando: El valor del gasto supere el monto de pesos un mil ($ 1.000,00). Se pueden presentar al menos tres (3) solicitudes de cotización (del bien o servicio a contratar) cursadas a tres o más empresas oferentes. La selección del proveedor se hará con el criterio del más bajo precio. En caso de no contar con tres (3) presupuestos, o no poder seleccionar al proveedor que ofrece menor precio, presentar este cuadro una nota de justificación siguiendo las pautas del ítem (XX)
A15: (b) Ejemplos: En el caso de viajes, indicar Origen/Destino (si corresponde también escalas) Si se tratara de servicios tipo catering, indicar las cantidades de asistentes, así como los días en que se demanda la prestación del servicio. Si fuera papelería indicar, cantidades de afiches, trípticos, etc.

Sheet Monitor Nosotros
D2: CUADRO DE COTIZACIONES
A5: Cuadro Comparativo de Cotizaciones
A7: Presupuestos (a) | B7: Empresa (Nombre fiscal de la empresa) | C7: NIT Dirección, Teléfono | D7: Descripción del bien/ servicio (b) Características de los bienes/ servicios | E7: Importe Unitario (moneda nacional) | F7: Importe Total IVA incluido (moneda nacional) | G7: Importe Total (moneda extranjera) | H7: Tipo de cambio | I7: Forma de Pago (Contado o Cheque) | J7: Observaciones (se debe incluir toda aquella característica que no ha sido posible incluir anteriormente)
A8: Nº 1 | B8: Amazon | C8: 901180732-2 901003327 Ambos registrados en Bogotá, D.C. | D8: Acer Monitor de 27 pulgadas - Pantalla FHD IPS KB272-27 pulgadas (1920 x 1080), frecuencia de actualización de hasta 120 Hz, 99% sRGB, inclinación, compatibilidad de sincronización adaptativa https://www.amazon.com/Acer-Monitor-pulgadas-compatibilidad-sincronizaci%C3%B3n/dp/B0D9MK23S7?th=1&language=es_US&currency=COP | E8: 365207 | F8: 365207 | G8: 100.34 | H8: 3.679,25 | I8: Tarjetas de Crédito y Débito: Visa, Mastercard y American Express. Amazon Recargable: Tarjeta prepagada propia de Amazon. Pago en Efectivo: En tiendas OXXO y otros establecimientos participantes (se genera un código de barras). | J8: 30 días a 1 año de garantia
A9: Nº2 | B9: Mercado Libre | C9: 830067394-6 Carrera 17 No. 93 - 09, Bogotá D.C.MercadoLibre | D9: Monitor Aoc 22b35hm23 Led Full Hd 22 120hz Con Hdmi Y Vga Negro https://www.mercadolibre.com.co/monitor-aoc-22b35hm23-led-full-hd-22-120hz-con-hdmi-y-vga-negro/p/MCO57030646?pdp_filters=item_id%3AMCO3706011738&from=gshop&matt_tool=32927594&matt_word=&matt_source=google&matt_campaign_id=22126928795&matt_ad_group_id=173140665043&matt_match_type=&matt_network=g&matt_device=c&matt_creative=729917879993&matt_keyword=&matt_ad_position=&matt_ad_type=pla&matt_merchant_id=735127773&matt_product_id=MCO57030646-product&matt_product_partition_id=2388112038413&matt_target_id=aud-2200363567910:pla-2388112038413&cq_src=google_ads&cq_cmp=22126928795&cq_net=g&cq_plt=gp&cq_med=pla&gad_source=1&gad_campaignid=22126928795&gbraid=0AAAAAD1DcoxfrUg4jabDNUTsmAg75yfkl&gclid=Cj0KCQjws83OBhD4ARIsACblj185yFW1yg8KzpMWdpFYWWzKl0xAyKa12I-Icw5gkHuD8xm4BVN-t1waAs1SEALw_wcB | E9: 250000 | F9: 250000 | G9: 68.69 | H9: 3.679,25 | I9: Mercado Pago: Saldo disponible en la cuenta de Mercado Pago.Tarjetas de Débito: Visa y Mastercard. | J9: 1 año de garantía
A10: Nº 3 | B10: Falabella | C10: 900.017.447-8, 57 1 587 7776, Calle 99 # 11A – 32 | D10: Monitor Samsung Essential 24 S33GF FHD HDMI VGA 100Hz https://www.falabella.com.co/falabella-co/product/151085606/monitor-samsung-essential-24-s33gf-fhd-hdmi-vga-100hz/151085607?kid=shopp261fa&gclsrc=aw.ds&gad_source=4&gad_campaignid=21861273110&gbraid=0AAAAADtuoyRiS9fCQ81DE1qLD4RbYjXf_&gclid=Cj0KCQjws83OBhD4ARIsACblj19tmGFANehD-r9pyg-MvjP09-FfU25Njr-tHtRDEliWIHJG4Fp3PXsaAns6EALw_wcB | E10: 379000 | F10: 379000 | G10: 104.13 | H10: 3.679,25 | I10: Tarjetas de Crédito y Débito: Visa, Mastercard, American Express, Discover. Plataformas de pago: PayPal y Google Pay. Financiación: HP ofrece opciones de financiamiento para la compra de equipos. | J10: 1 año de garantía
A13: (a) Se deben presentar tres (3) presupuestos cuando: El valor del gasto supere el monto de pesos un mil ($ 1.000,00). Se pueden presentar al menos tres (3) solicitudes de cotización (del bien o servicio a contratar) cursadas a tres o más empresas oferentes. La selección del proveedor se hará con el criterio del más bajo precio. En caso de no contar con tres (3) presupuestos, o no poder seleccionar al proveedor que ofrece menor precio, presentar este cuadro una nota de justificación siguiendo las pautas del ítem (XX)
A15: (b) Ejemplos: En el caso de viajes, indicar Origen/Destino (si corresponde también escalas) Si se tratara de servicios tipo catering, indicar las cantidades de asistentes, así como los días en que se demanda la prestación del servicio. Si fuera papelería indicar, cantidades de afiches, trípticos, etc.

Sheet  Disco mecanico Nosotros
A1: M
D2: CUADRO DE COTIZACIONES
A5: Cuadro Comparativo de Cotizaciones
A7: Presupuestos (a) | B7: Empresa (Nombre fiscal de la empresa) | C7: NIT Dirección, Teléfono | D7: Descripción del bien/ servicio (b) Características de los bienes/ servicios | E7: Importe Unitario (moneda nacional) | F7: Importe Total IVA incluido (moneda nacional) | G7: Importe Total (moneda extranjera) | H7: Tipo de cambio | I7: Forma de Pago (Contado o Cheque) | J7: Observaciones (se debe incluir toda aquella característica que no ha sido posible incluir anteriormente)
A8: Nº 1 | B8: Mercado Libre | C8: 830067394-6 Carrera 17 No. 93 - 09, Bogotá D.C.MercadoLibre | D8: Disco duro interno Seagate Barracuda ST1000dm010 1TB https://articulo.mercadolibre.com.co/MCO-639015765-disco-duro-interno-seagate-barracuda-1tb-_JM#polycard_client=search-desktop&search_layout=grid&position=8&type=item&tracking_id=acb2fb39-cf45-4602-b246-b0364def2165&wid=MCO639015765&sid=search | E8: 199000 | F8: 199000 | G8: 54.67 | H8: 3.679,25 | I8: Mercado Pago: Saldo disponible en la cuenta de Mercado Pago.Tarjetas de Débito: Visa y Mastercard. | J8: Garantia de 1 mes (del vendedor)
A9: Nº2 | B9: Falabella | C9: 900.017.447-8, 57 1 587 7776, Calle 99 # 11A – 32 | D9: Disco duro para pc 1tb western digital - wd10ezex https://www.falabella.com.co/falabella-co/product/118334759/Disco-duro-para-pc-1tb-western-digital-wd10ezex/118334761 | E9: 215900 | F9: 215900 | G9: 58.85 | H9: 3.679,25 | I9: tarjeta Falabella, tarjeta credito, efectivo | J9: Tienes 5 días hábiles para devolver por ley. Tienes 30 días calendario desde que recibes el producto para pedir su devolución.
A10: Nº 3 | B10: Mercado Libre | C10: 830067394-6 Carrera 17 No. 93 - 09, Bogotá D.C.MercadoLibre | D10: Disco Duro Externo Portatil Toshiba 1 Tb Usb 3.0 Color Negro https://www.mercadolibre.com.co/disco-duro-externo-portatil-toshiba-1-tb-usb-30-color-negro/p/MCO32418108#polycard_client=search-desktop&search_layout=grid&position=2&type=product&tracking_id=375dd9e9-ff10-4881-9fb7-5ff648a18285&wid=MCO2330174032&sid=search | E10: 319900 | F10: 319900 | G10: 87.88 | H10: 3.679,25 | I10: Mercado Pago: Saldo disponible en la cuenta de Mercado Pago.Tarjetas de Débito: Visa y Mastercard. | J10: 1 mes para devolucion
A13: (a) Se deben presentar tres (3) presupuestos cuando: El valor del gasto supere el monto de pesos un mil ($ 1.000,00). Se pueden presentar al menos tres (3) solicitudes de cotización (del bien o servicio a contratar) cursadas a tres o más empresas oferentes. La selección del proveedor se hará con el criterio del más bajo precio. En caso de no contar con tres (3) presupuestos, o no poder seleccionar al proveedor que ofrece menor precio, presentar este cuadro una nota de justificación siguiendo las pautas del ítem (XX)
A15: (b) Ejemplos: En el caso de viajes, indicar Origen/Destino (si corresponde también escalas) Si se tratara de servicios tipo catering, indicar las cantidades de asistentes, así como los días en que se demanda la prestación del servicio. Si fuera papelería indicar, cantidades de afiches, trípticos, etc.

Sheet  Servidor Nosotros
D2: CUADRO DE COTIZACIONES
A5: Cuadro Comparativo de Cotizaciones
A7: Presupuestos (a) | B7: Empresa (Nombre fiscal de la empresa) | C7: NIT Dirección, Teléfono | D7: Descripción del bien/ servicio (b) Características de los bienes/ servicios | E7: Importe Unitario (moneda nacional) | F7: Importe Total IVA incluido (moneda nacional) | G7: Importe Total (moneda extranjera) | H7: Tipo de cambio | I7: Forma de Pago (Contado o Cheque) | J7: Observaciones (se debe incluir toda aquella característica que no ha sido posible incluir anteriormente)
A8: Nº 1 | B8: Bluehost | C8: Headquarters: Jacksonville, Florida. Company Entity: Owned by Newfold Digital. Support & Sales Contact: 1-855-372-3679. | D8: Ofrece hosting compartido, hosting dedicado y servidores virtuales privados (VPS). Además, incluye registro de dominios, correos electrónicos profesionales, creadores de sitios web (con IA) y certificados SSL. https://www.bluehost.com/pricing-and-plans?utm_campaign=brand_PPC&utm_source=googleads&utm_medium=brandsearch&channelid=P61C101S570N0B5578A2D4499E0000V901&siteid=46097236&gclsrc=aw.ds&gad_source=1&gad_campaignid=22901189979&gbraid=0AAAAADtGWPJCqV7uqcxDdvE1HAZTCw05N&gclid=CjwKCAjw1tLOBhAMEiwAiPkRHjNyo_Q8Sy0ZXRi0JAPleXOqAVMLw8MjT7AclvHiHHONrM1fJ8zxgBoCeDMQAvD_BwE | E8: 4000 | F8: 4000 | G8: 0,94 | H8: 3.679,25 | I8: Tarjetas de crédito y débito: VISA, MasterCard, American Express, Discover. PayPal: Se puede usar para pagos únicos y renovaciones automáticas. | J8: Renovación automática: Por defecto, Bluehost renueva automáticamente los servidores dedicados, intentando realizar el cargo 15 días antes del vencimiento utilizando el método de pago registrado.
A9: Nº2 | B9: CasaOS/Ubuntu Server | C9: La combinación deCasaOS sobre Ubuntu transforma un ordenador o servidor (incluidos mini PCs y Raspberry Pi) en una nube privada, un NAS (almacenamiento en red) o un servidor doméstico de alto rendimiento, gestionado a través de una interfaz gráfica moderna y sencilla. | D9: La combinación de CasaOS sobre Ubuntu Server es una solución popular para montar un servidor doméstico (homelab) o nube privada. Básicamente, utiliza la potencia y estabilidad de Ubuntu Server como base, y añade la interfaz gráfica intuitiva de CasaOS para gestionar aplicaciones y contenedores Docker sin necesidad de usar la línea de comandos. https://casaos.zimaspace.com/ | E9: no tiene costo de licencia | F9: no tiene costo de licencia | G9: no tiene costo de licencia | H9: 3.679,26 | I9: no aplica | J9: por ser codigo abierto no tiene garantia
A10: Nº 3 | B10: OpenMediaVault | C10: OpenMediaVault (OMV)sirve principalmente como un sistema operativo basado en Debian Linux para convertir hardware genérico (como PCs viejas, servidores o Raspberry Pi) en un Servidor de Almacenamiento Conectado a la Red (NAS). Funciona como una solución gratuita y de código abierto para centralizar datos, gestionar permisos y compartir archivos en una red local o remota | D10: OpenMediaVault (OMV)es una solución de almacenamiento conectado a la red (NAS) de próxima generación, basada en Debian Linux y diseñada para convertir computadoras, servidores o Raspberry Pi en servidores de almacenamiento centralizados. https://www.openmediavault.org/ | E10: no tiene costo de licencia | F10: no tiene costo de licencia | G10: no tiene costo de licencia | H10: 3.679,27 | I10: no aplica | J10: por ser codigo abierto no tiene garantia
A13: (a) Se deben presentar tres (3) presupuestos cuando: El valor del gasto supere el monto de pesos un mil ($ 1.000,00). Se pueden presentar al menos tres (3) solicitudes de cotización (del bien o servicio a contratar) cursadas a tres o más empresas oferentes. La selección del proveedor se hará con el criterio del más bajo precio. En caso de no contar con tres (3) presupuestos, o no poder seleccionar al proveedor que ofrece menor precio, presentar este cuadro una nota de justificación siguiendo las pautas del ítem (XX)
A15: (b) Ejemplos: En el caso de viajes, indicar Origen/Destino (si corresponde también escalas) Si se tratara de servicios tipo catering, indicar las cantidades de asistentes, así como los días en que se demanda la prestación del servicio. Si fuera papelería indicar, cantidades de afiches, trípticos, etc.

Sheet  ram nosotros
D2: CUADRO DE COTIZACIONES
A5: Cuadro Comparativo de Cotizaciones
A7: Presupuestos (a) | B7: Empresa (Nombre fiscal de la empresa) | C7: NIT Dirección, Teléfono | D7: Descripción del bien/ servicio (b) Características de los bienes/ servicios | E7: Importe Unitario (moneda nacional) | F7: Importe Total IVA incluido (moneda nacional) | G7: Importe Total (moneda extranjera) | H7: Tipo de cambio | I7: Forma de Pago (Contado o Cheque) | J7: Observaciones (se debe incluir toda aquella característica que no ha sido posible incluir anteriormente)
A8: Nº 1 | B8: Mercado libre | C8: 830067394-6 Carrera 17 No. 93 - 09, Bogotá D.C.MercadoLibre | D8: Memoria RAM Premier color verde 16GB 1x16GB Adata AD4S320016G22-SGN https://www.mercadolibre.com.co/memoria-ram-premier-color-verde-16gb-1x16gb-adata-ad4s320016g22-sgn/p/MCO18724279 | E8: 470000 | F8: 470000 | G8: 127.4 | H8: 3.679,25 | I8: Mercado Pago: Saldo disponible en la cuenta de Mercado Pago.Tarjetas de Débito: Visa y Mastercard. | J8: 30 dias de devolucion
A9: Nº2 | B9: Mercado libre | C9: 830067394-6 Carrera 17 No. 93 - 09, Bogotá D.C.MercadoLibre | D9: Timetec 16gb Ddr4 2400mhz Pc4-19200 https://articulo.mercadolibre.com.co/MCO-1654528271-memoria-ram-timetec-16-gb-ddr4-2400-mhz-pc4-19200-udimm-_JM#polycard_client=search-desktop&search_layout=grid&position=9&type=item&tracking_id=561495b0-af11-428d-aae5-9a47b3d95643 | E9: 616678 | F9: 616678 | G9: 169.4 | H9: 3.679,25 | I9: Mercado Pago: Saldo disponible en la cuenta de Mercado Pago.Tarjetas de Débito: Visa y Mastercard. | J9: 30 dias de devolucion
A10: Nº 3 | B10: Exito | C10: 890900.608-9, Carrera 48 N° 32B SUR 139, (604) 6049696 | D10: Memoria Ram 16Gb Ddr4 3200Mhz Attech https://www.exito.com/memoria-ram-16gb-ddr4-3200mhz-attech-para-portatil-104852224-mp/p | E10: 599000 | F10: 599000 | G10: 162.36 | H10: 3.679,25 | I10: tarjetas Éxito, tarjetas débito/crédito, PSE, Nequi, Puntos Colombia, Addi y pago contra entrega | J10: 12 meses de garantia
D11: Memoria Ram 16Gb Ddr4 3200Mhz Attech Para Portatil
A13: (a) Se deben presentar tres (3) presupuestos cuando: El valor del gasto supere el monto de pesos un mil ($ 1.000,00). Se pueden presentar al menos tres (3) solicitudes de cotización (del bien o servicio a contratar) cursadas a tres o más empresas oferentes. La selección del proveedor se hará con el criterio del más bajo precio. En caso de no contar con tres (3) presupuestos, o no poder seleccionar al proveedor que ofrece menor precio, presentar este cuadro una nota de justificación siguiendo las pautas del ítem (XX)
A15: (b) Ejemplos: En el caso de viajes, indicar Origen/Destino (si corresponde también escalas) Si se tratara de servicios tipo catering, indicar las cantidades de asistentes, así como los días en que se demanda la prestación del servicio. Si fuera papelería indicar, cantidades de afiches, trípticos, etc.

Sheet Consolidado
B4: Datos del cliente
B5: Nombre: | D5: Spa New Boys
B6: NIT: | D6: 901.456.782-3
B7: Dirección: | D7: Cra 80 #70-22, Bogotá
B8: Teléfono: | D8: 312 456 7890
B9: Datos del equipo
B10: Marca | D10: Modelo
B11: Sistema Operativo
B12: Descripcion | C12: Marca | D12: Modelo | E12: Estado | F12: Justificación
B13: ='Torre admin'!D8 -> PC GAMER AMD RYZEN 5 5600G A520M WIFI 16GB 512 M2 VEGA 7 | C13: PC GAMER AMD RYZEN 5 | D13: A520M | E13: propuesto | F13: Se eligió por su procesador Ryzen 5 con gráficos integrados y 16GB de RAM, ofreciendo buen rendimiento y fluidez sin necesidad de tarjeta gráfica adicional. ademas de tener un percio accesible
B14: ='Monitor Admin'!D9 -> MONITOR ACER 22" EK220Q 100Hz 1Ms 1920 X 1080 VA HDMI + VGA | C14: ='Monitor Admin'!D9 -> MONITOR ACER 22" EK220Q 100Hz 1Ms 1920 X 1080 VA HDMI + VGA | D14: EK220Q | E14: propuesto | F14: Se seleccionó por su resolución Full HD y 100Hz, que brindan buena calidad de imagen y fluidez visual.
B15: Disco de Estado Sólido 2.5 512GB SATA XUE® BLINK S500/512 550MB/S | C15: BLINK S500/512. | D15: XUE BLINK S500/512 | E15: propuesto | F15: Se eligió por su capacidad y mayor velocidad frente a discos duros, mejorando el rendimiento del sistema.
B16: ='Disco duro interno Admin'!D8 -> Unidad solida M2 Xpress Legend 710 de 512 Gb Adata | C16: Adata | D16: M2 Xpress Legend 710 | E16: propuesto | F16: Se seleccionó por su alta velocidad de lectura y escritura, optimizando el rendimiento del equipo.
B17: Memoria RAM ADATA 16Gb DDR4 3200 PC | C17: Adata | D17: ADATA Premier 16GB DDR4 3200 AD4U320016G22-SGN | E17: propuesto | F17: Se eligió por su capacidad de 16GB y frecuencia de 3200MHz, lo que asegura un buen desempeño en multitarea y ejecución de aplicaciones, manteniendo estabilidad y rapidez en el sistema.
B18: Servicio de hosting de Paginas web | C18: donweb | D18: No aplica | E18: propuesto | F18: Se seleccionó este servicio debido a su capacidad de almacenamiento y recursos disponibles, lo que permite alojar páginas web de manera eficiente, garantizando estabilidad y buen rendimiento.
B19: Servicio de hosting de Paginas web | C19: HostGator | D19: No aplica | E19: propuesto | F19: Se eligió este proveedor por su alta disponibilidad de servidores, buen rendimiento y reconocimiento en el mercado, lo que garantiza confiabilidad y soporte para proyectos web.
B20: Teclado USB Jaltech forza KB 05 | C20: Jaltech | D20: Teclado USB Forza Jaltech KB-05 | E20: propuesto | F20: Se seleccionó este teclado por su diseño ergonómico y conexión USB plug-and-play, facilitando su uso sin configuraciones adicionales, además de ofrecer comodidad para largas jornadas de trabajo.
B21: Mouse Usb Logitech M90 Negro | C21: Logitech | D21: Logitech M90 | E21: propuesto | F21: Se eligió este mouse por su precisión y sensor óptico confiable, además de su diseño sencillo y cómodo que lo hace adecuado para uso continuo en tareas de oficina.
B22: Pc gamer esencial | C22: ACER | D22: Combo de computador | E22: propuesto | F22: Se seleccionó por ser un equipo completo, compatible y fácil de instalar. Ademas su precio sale mas rentable, por esto consideramos que es mejor opcion comprarlo de esta manera en lugar de por partes.
B23: Computador AMD Ryzen 5 | C23: ACER | D23: Combo de computador | E23: propuesto | F23: Este es una buena segunda opcion y se eligió por su buen rendimiento gracias al procesador Ryzen 5, aunque su precio es más alto frente a opciones similares.
B24: Portatil Asus Vivobook 15 | C24: ASUS | D24: Vivobook 15 M1502 | E24: Propuesto | F24: Se eligió por su procesador Ryzen 7 y 16GB de RAM, que ofrecen un excelente rendimiento en multitarea y eficiencia energética, junto con SSD de 512GB que mejora la velocidad del sistema.
B28: Reporte de mantenimiento
B30: Firmas de comformidad
B31: Por el cliente | E31: por la empresa

Sheet Tarjeta de video nosotros
D2: CUADRO DE COTIZACIONES
A5: Cuadro Comparativo de Cotizaciones
A7: Presupuestos (a) | B7: Empresa (Nombre fiscal de la empresa) | C7: NIT Dirección, Teléfono | D7: Descripción del bien/ servicio (b) Características de los bienes/ servicios | E7: Importe Unitario (moneda nacional) | F7: Importe Total IVA incluido (moneda nacional) | G7: Importe Total (moneda extranjera) | H7: Tipo de cambio | I7: Forma de Pago (Contado o Cheque) | J7: Observaciones (se debe incluir toda aquella característica que no ha sido posible incluir anteriormente)
A8: Nº 1 | B8: Speed Logic | C8: 900.041.754-5, Calle 77 # 16-20. 301 7204749 | D8: ASUS Dual GeForce RTX™ 3050 OC Edition 6GB GDDR6 con dos potentes ventiladores Rendimiento de juegos AAA. https://speedlogic.com.co/tienda/tarjetas-graficas/nvidia/tarjeta-de-video-nvidia-geforce-asus-rtx-3050-dual-oc-auto-ex-6-gigas/?srsltid=AfmBOoqg_EtgLot8X-RAR43LAG-LoS0XVaSITYZSn3uMzGvlACYI0OUf | E8: 1189000 | F8: 1189000 | G8: 326.62 | H8: 3.679,25 | I8: consignaciones bancarias (Davivienda/Bancolombia), giros nacionales (Efecty, Baloto, Pagatodo) y pagos en línea a través de PayU o EpayCO | J8: sin garantia
A9: Nº2 | B9: Amazon | C9: 901180732-2 901003327 Ambos registrados en Bogotá, D.C. | D9: ASRock AMD Radeon RX 7600 Challenger 8 GB OC GDDR6 https://www.amazon.com/-/es/ASRock-Challenger-DisplayPort-Enfriamiento-Silencioso/dp/B0C626FFG2 | E9: 1022646 | F9: 1022646 | G9: 280.92 | H9: 3.679,25 | I9: Tarjetas de Crédito y Débito: Visa, Mastercard y American Express. Amazon Recargable: Tarjeta prepagada propia de Amazon. Pago en Efectivo: En tiendas OXXO y otros establecimientos participantes (se genera un código de barras). | J9: 30 dias devolucion
A10: Nº 3 | B10: Mercado Libre | C10: 830067394-6 Carrera 17 No. 93 - 09, Bogotá D.C.MercadoLibre | D10: Tarjeta De Video Gigabyte Radeon Rx 7600 Gaming Oc 8g Gddr6 https://www.mercadolibre.com.co/tarjeta-de-video-gigabyte-radeon-rx-7600-gaming-oc-8g-gddr6/p/MCO27793940 | E10: 1610000 | F10: 1610000 | G10: 434.28 | H10: 3.679,25 | I10: Mercado Pago: Saldo disponible en la cuenta de Mercado Pago.Tarjetas de Débito: Visa y Mastercard. | J10: 30 dias devolucion
A13: (a) Se deben presentar tres (3) presupuestos cuando: El valor del gasto supere el monto de pesos un mil ($ 1.000,00). Se pueden presentar al menos tres (3) solicitudes de cotización (del bien o servicio a contratar) cursadas a tres o más empresas oferentes. La selección del proveedor se hará con el criterio del más bajo precio. En caso de no contar con tres (3) presupuestos, o no poder seleccionar al proveedor que ofrece menor precio, presentar este cuadro una nota de justificación siguiendo las pautas del ítem (XX)
A15: (b) Ejemplos: En el caso de viajes, indicar Origen/Destino (si corresponde también escalas) Si se tratara de servicios tipo catering, indicar las cantidades de asistentes, así como los días en que se demanda la prestación del servicio. Si fuera papelería indicar, cantidades de afiches, trípticos, etc.

Sheet Procesador Nosotros
D2: CUADRO DE COTIZACIONES
A5: Cuadro Comparativo de Cotizaciones
A7: Presupuestos (a) | B7: Empresa (Nombre fiscal de la empresa) | C7: NIT Dirección, Teléfono | D7: Descripción del bien/ servicio (b) Características de los bienes/ servicios | E7: Importe Unitario (moneda nacional) | F7: Importe Total IVA incluido (moneda nacional) | G7: Importe Total (moneda extranjera) | H7: Tipo de cambio | I7: Forma de Pago (Contado o Cheque) | J7: Observaciones (se debe incluir toda aquella característica que no ha sido posible incluir anteriormente)
A8: Nº 1 | B8: Mercado Libre | C8: 830067394-6 Carrera 17 No. 93 - 09, Piso 3°, Bogotá D.C.MercadoLibre | D8: Procesador gamer Intel Core i5-12400F BX8071512400F de 6 núcleos y 4.4GHz de frecuencia https://www.mercadolibre.com.co/procesador-gamer-intel-core-i5-12400f-bx8071512400f-de-6-nucleos-y-44ghz-de-frecuencia/p/MCO18733972#polycard_client=search-desktop&search_layout=grid&position=5&type=product&tracking_id=d310df42-6d23-4042-be54-551fd42f7c86&wid=MCO3713302828&sid=search | E8: 687679 | F8: 687679 | G8: 188.91 | H8: 3.679,25 | I8: Mercado Pago: Saldo disponible en la cuenta de Mercado Pago.Tarjetas de Débito: Visa y Mastercard. | J8: 30 dias de devolucion
A9: Nº2 | B9: Mercado Libre | C9: 830067394-6 Carrera 17 No. 93 - 09, Piso 3°, Bogotá D.C.MercadoLibre | D9: Procesador AMD Ryzen 5 5600G de 6 núcleos 12 hilos https://www.mercadolibre.com.co/procesador-amd-ryzen-5-5600gt-6-nucleos-am4-grafica-radeon/p/MCO32444906#polycard_client=recommendations_pdp-v2p&reco_backend=ranker_retrieval_system_org&reco_model=coldstart_low_exposition&reco_client=pdp-v2p&reco_item_pos=0&reco_backend_type=low_level&reco_id=ae481b39-9ffb-4579-8852-0f71b1bbf312&wid=MCO2799695908&sid=recos | E9: 800000 | F9: 800000 | G9: 219,76 | H9: 3.679,25 | I9: Mercado Pago: Saldo disponible en la cuenta de Mercado Pago.Tarjetas de Débito: Visa y Mastercard. | J9: 30 dias de devolucion
A10: Nº 3 | B10: Amazon | C10: 901180732-2 901003327 Ambos registrados en Bogotá, D.C. | D10: es un procesador de gama media-alta diseñado específicamente para entusiastas del gaming y la productividad que buscan dar el salto a la plataforma AM5 Modelo: 7600X. https://www.amazon.com/-/es/AMD-Procesador-desbloqueado-RyzenTM-9600X/dp/B0D6NN6TM7/ref=sr_1_3?__mk_es_US=%C3%85M%C3%85%C5%BD%C3%95%C3%91&crid=1AH9NA5Z0VQJN&dib=eyJ2IjoiMSJ9.z9fq0_6wXHuqejIEi2t8ldmGAKLVL7fdOStrySIhFgDdYhdp0KtgXIrN9EhJ6pxu8aoLNky7H3QLz6rC0jliEBFIHXasKAgbWITx-Ip5rBbng-Uq1TEYpsws__2PD-HwCw_1E1UAgta6CQ0EwOI2Y51Y4zsilwTR__AkYwl5xZ11QHtMD9Qypz07OVV6rTRXWBvDVtOp3rESfBm46xfZp3gIex0rz7d6JUMpQUtadgc.xmTWwP29NjQBaY1qOSBmTfdYW6FFdTRQ1bmn82x4-ws&dib_tag=se&keywords=Procesador%2BGamer%2BAMD%2BRyzen%2B5%2B7600X&qid=1775520498&sprefix=procesador%2Bgamer%2Bamd%2Bryzen%2B5%2B7600x%2B%2Caps%2C159&sr=8-3&th=1 | E10: 686622 | F10: 686622 | G10: 188.54 | H10: 3.679,25 | I10: Licenciamiento de Patentes y Venta de Chipsets: Las transacciones son corporativas y directas con los fabricantes de equipos originales (OEMs). | J10: 30 dias de devolucion
A13: (a) Se deben presentar tres (3) presupuestos cuando: El valor del gasto supere el monto de pesos un mil ($ 1.000,00). Se pueden presentar al menos tres (3) solicitudes de cotización (del bien o servicio a contratar) cursadas a tres o más empresas oferentes. La selección del proveedor se hará con el criterio del más bajo precio. En caso de no contar con tres (3) presupuestos, o no poder seleccionar al proveedor que ofrece menor precio, presentar este cuadro una nota de justificación siguiendo las pautas del ítem (XX)
A15: (b) Ejemplos: En el caso de viajes, indicar Origen/Destino (si corresponde también escalas) Si se tratara de servicios tipo catering, indicar las cantidades de asistentes, así como los días en que se demanda la prestación del servicio. Si fuera papelería indicar, cantidades de afiches, trípticos, etc.

Sheet Teclado nosostros 
D2: CUADRO DE COTIZACIONES
A5: 0
A7: Presupuestos (a) | B7: Empresa (Nombre fiscal de la empresa) | C7: NIT Dirección, Teléfono | D7: Descripción del bien/ servicio (b) Características de los bienes/ servicios | E7: Importe Unitario (moneda nacional) | F7: Importe Total IVA incluido (moneda nacional) | G7: Importe Total (moneda extranjera) | H7: Tipo de cambio | I7: Forma de Pago (Contado o Cheque) | J7: Observaciones (se debe incluir toda aquella característica que no ha sido posible incluir anteriormente)
A8: Nº 1 | B8: falabella | C8: 900.047.981-8 , cuenta con multiples locales, 018000 958780 | D8: Teclado USB Genius Smart KB-100 https://www.falabella.com.co/falabella-co/product/140143182/Teclado-USB-Genius-Smart-KB-100-Con-Teclas-12-Multimedia-FN/140143183 | E8: 39900 | F8: 39900 | G8: 10.82 | H8: 3679,25 | I8: Tarjeta CMR (crédito y débito), otras tarjetas de crédito/débito bancarias, PSE para cuentas de ahorros, CMR Puntos, Gift Cards y pago en efectivo | J8: Sin garantia
A9: Nº2 | B9: Exito | C9: 890900.608-9, Carrera 48 N° 32B SUR 139, (604) 6049696 | D9: Teclado Hp 125 Alámbrico Usb Negro Español https://www.exito.com/teclado-hp-125-alambrico-usb-negro-espanol-104852239-mp/p | E9: 39900 | F9: 39900 | G9: 10.82 | H9: 3.679,25 | I9: tarjetas Éxito, tarjetas débito/crédito, PSE, Nequi, Puntos Colombia, Addi y pago contra entrega | J9: 3 meses de garantia
A10: Nº 3 | B10: Mercado Libre | C10: 830067394-6 Carrera 17 No. 93 - 09, Piso 3°, Bogotá D.C.MercadoLibre | D10: Maxell Teclado Alambrico Kb-90 https://www.mercadolibre.com.co/maxell-teclado-alambr-kb-90-basico/p/MCO19931301 | E10: 43900 | F10: 43900 | G10: 11.91 | H10: 3.679,25 | I10: Mercado Pago: Saldo disponible en la cuenta de Mercado Pago.Tarjetas de Débito: Visa y Mastercard. | J10: 30 dias de devolucion
H11: 3.679,28
A13: (a) Se deben presentar tres (3) presupuestos cuando: El valor del gasto supere el monto de pesos un mil ($ 1.000,00). Se pueden presentar al menos tres (3) solicitudes de cotización (del bien o servicio a contratar) cursadas a tres o más empresas oferentes. La selección del proveedor se hará con el criterio del más bajo precio. En caso de no contar con tres (3) presupuestos, o no poder seleccionar al proveedor que ofrece menor precio, presentar este cuadro una nota de justificación siguiendo las pautas del ítem (XX)
A15: (b) Ejemplos: En el caso de viajes, indicar Origen/Destino (si corresponde también escalas) Si se tratara de servicios tipo catering, indicar las cantidades de asistentes, así como los días en que se demanda la prestación del servicio. Si fuera papelería indicar, cantidades de afiches, trípticos, etc.

Sheet Mouse nosotros
D2: CUADRO DE COTIZACIONES
A5: Cuadro Comparativo de Cotizaciones
A7: Presupuestos (a) | B7: Empresa (Nombre fiscal de la empresa) | C7: NIT Dirección, Teléfono | D7: Descripción del bien/ servicio (b) Características de los bienes/ servicios | E7: Importe Unitario (moneda nacional) | F7: Importe Total IVA incluido (moneda nacional) | G7: Importe Total (moneda extranjera) | H7: Tipo de cambio | I7: Forma de Pago (Contado o Cheque) | J7: Observaciones (se debe incluir toda aquella característica que no ha sido posible incluir anteriormente)
A8: Nº 1 | B8: Falabella | C8: 900.047.981-8 , cuenta con multiples locales, 018000 958780 | D8: Mouse Logitech M90 Usb. Instalación rápida y fácil, puede conectar el cable a un puerto USB y usarlo inmediatamente https://www.falabella.com.co/falabella-co/product/120778408/Mouse-Logitech-M90-Usb/120778409 | E8: 31900 | F8: 31900 | G8: 8.76 | H8: 3.679,25 | I8: tarjetas bancarias, efectivo en establecimientos seleccionados y opciones de pago digital | J8: 1 año de garantía por defectos de fabricación directamente con LOGITECH.
A9: Nº2 | B9: Mercado Libre | C9: 830067394-6 Carrera 17 No. 93 - 09, Bogotá D.C.MercadoLibre | D9: Mouse Dell MS116 negro. Compatibilidad con Windows 10. 7. 8.1. 11. Linux. Chrome OS. Android. https://www.mercadolibre.com.co/mouse-dell-ms116-negro/p/MCO6332790 | E9: 28370 | F9: 28370 | G9: 7.79 | H9: 3.679,25 | I9: Mercado Pago: Saldo disponible en la cuenta de Mercado Pago.Tarjetas de Débito: Visa y Mastercard. | J9: 30 dias de devolucion
A10: Nº 3 | B10: Mercado Libre | C10: 830067394-6 Carrera 17 No. 93 - 09, Piso 3°, Bogotá D.C.MercadoLibre | D10: Mouse ESENSES Inalámbrico Óptico WOM 2000-Negros https://www.mercadolibre.com.co/mouse-inalambrico-marca--esenses-1000-dpi-wom-1010/up/MCOU3842376372#polycard_client=recommendations_vip-v2p&reco_backend=ranker_retrieval_system_org&reco_model=rk_ent_v3_retsys_org&reco_client=vip-v2p&reco_item_pos=1&reco_backend_type=low_level&reco_id=30c5e1a3-7b01-45ad-aa7f-6a4e19091b0b&wid=MCO1854512255&sid=recos | E10: 20999 | F10: 20999 | G10: 5.65 | H10: 3.679,25 | I10: tarjetas de crédito (Visa, Mastercard, American Express), PSE (débito bancario), Baloto, Efecty y consignación bancaria | J10: 30 dias de garantia
A13: (a) Se deben presentar tres (3) presupuestos cuando: El valor del gasto supere el monto de pesos un mil ($ 1.000,00). Se pueden presentar al menos tres (3) solicitudes de cotización (del bien o servicio a contratar) cursadas a tres o más empresas oferentes. La selección del proveedor se hará con el criterio del más bajo precio. En caso de no contar con tres (3) presupuestos, o no poder seleccionar al proveedor que ofrece menor precio, presentar este cuadro una nota de justificación siguiendo las pautas del ítem (XX)
A15: (b) Ejemplos: En el caso de viajes, indicar Origen/Destino (si corresponde también escalas) Si se tratara de servicios tipo catering, indicar las cantidades de asistentes, así como los días en que se demanda la prestación del servicio. Si fuera papelería indicar, cantidades de afiches, trípticos, etc.

Sheet software licencia
D2: CUADRO DE COTIZACIONES
A5: Cuadro Comparativo de Cotizaciones
A7: Presupuestos (a) | B7: Empresa (Nombre fiscal de la empresa) | C7: NIT Dirección, Teléfono | D7: Descripción del bien/ servicio (b) Características de los bienes/ servicios | E7: Importe Unitario (moneda nacional) | F7: Importe Total IVA incluido (moneda nacional) | G7: Importe Total (moneda extranjera) | H7: Tipo de cambio | I7: Forma de Pago (Contado o Cheque) | J7: Observaciones (se debe incluir toda aquella característica que no ha sido posible incluir anteriormente)
A8: Nº 1 | B8: Microsoft Coporation | C8: 91-1144442 (EE. UU.)One Microsoft Way, Redmond, Washington 98052, Estados Unidos | D8: Desarrolla software como Windows y Office; soluciones empresariales y nube. | E8: $500.000 – $800.000 COP (pago único o suscripción anual) | F8: $714.000 COP | G8: 150 – 200 USD | H8: 3.679,25 | I8: (tarjeta / pago inmediato) | J8: Licencia propietaria; requiere pago para uso legal. Puede incluir actualizaciones y soporte según el plan.
A9: Nº2 | B9: Canonical Ltd | C9: No. 05515334 (Reino Unido)5th Floor, Blue Fin Building, 110 Southwark Street, Londres, Reino Unido | D9: Mantiene Ubuntu; sistemas operativos y servicios de soporte open source. | E9: $400.000+ COP/año | F9: $476.000 COP con IVA | G9: 100 USD/año | H9: 3.679,25 | I9: (especialmente en soporte) | J9: Ubuntu es gratuito y de código abierto. El soporte técnico es opcional y de pago
A10: Nº 3 | B10: Google LLC | C10: EIN 77-0493581 (EE. UU.)1600 Amphitheatre Parkway, Mountain View, California 94043, Estados Unidos | D10: Ofrece servicios digitales como buscador, Chrome y herramientas en la nube. | E10: $25.000 – $60.000 COP/mes por usuario | F10: $35.700 COP/mes | G10: 6 – 12 USD/mes por usuario | H10: 3.679,25 | I10: (suscripción mensual automática) | J10: Modelo freemium: gratis con opciones premium.
G11: =F11+E11 -> 0
A13: (a) Se deben presentar tres (3) presupuestos cuando: El valor del gasto supere el monto de pesos un mil ($ 1.000,00). Se pueden presentar al menos tres (3) solicitudes de cotización (del bien o servicio a contratar) cursadas a tres o más empresas oferentes. La selección del proveedor se hará con el criterio del más bajo precio. En caso de no contar con tres (3) presupuestos, o no poder seleccionar al proveedor que ofrece menor precio, presentar este cuadro una nota de justificación siguiendo las pautas del ítem (XX)
A15: (b) Ejemplos: En el caso de viajes, indicar Origen/Destino (si corresponde también escalas) Si se tratara de servicios tipo catering, indicar las cantidades de asistentes, así como los días en que se demanda la prestación del servicio. Si fuera papelería indicar, cantidades de afiches, trípticos, etc.

Sheet licencia visual
A1: NIT Dirección, Teléfono
D2: CUADRO DE COTIZACIONES
A5: Cuadro Comparativo de Cotizaciones
A7: Presupuestos (a) | B7: Empresa (Nombre fiscal de la empresa) | C7: NIT Dirección, Teléfono | D7: Descripción del bien/ servicio (b) Características de los bienes/ servicios | E7: Importe Unitario (moneda nacional) | F7: Importe Total IVA incluido (moneda nacional) | G7: Importe Total (moneda extranjera) | H7: Tipo de cambio | I7: Forma de Pago (Contado o Cheque) | J7: Observaciones (se debe incluir toda aquella característica que no ha sido posible incluir anteriormente)
A8: Nº 1 | B8: Creative Commons (CC BY) | C8: 444 Castro Street, Suite 900, Mountain View, California, Estados Unidos | D8: Permite uso comercial Permite modificaciones Obligatorio dar crédito al autor | E8: $0 COP (gratuita) | F8: $0 COP | G8: 0 USD | H8: 3.679,25 | I8: (gratuita) | J8: Permite uso comercial sin restricciones adicionales. No exige compartir con la misma licencia. Solo requiere atribución al autor.
A9: Nº2 | B9: Creative Commons (CC BY-NC) | C9: 444 Castro Street, Suite 900, Mountain View, California, Estados Unidos | D9: No permite uso comercial Permite modificar Requiere atribución | E9: $0 COP (gratuita) | F9: $0 COP | G9: 0 USD | H9: 3.679,25 | I9: (gratuita) | J9: Prohíbe cualquier uso con fines comerciales. Puede generar dudas en qué se considera “comercial”. Requiere atribución al autor.
A10: Nº 3 | B10: Creative Commons (CC BY-SA) | C10: 444 Castro Street, Suite 900, Mountain View, California, Estados Unidos | D10: Permite uso comercial Permite modificar Debe conservar la misma licencia Requiere atribución | E10: $0 COP (gratuita) | F10: $0 COP | G10: 0 USD | H10: 3.679,25 | I10: (gratuita) | J10: Obliga a licenciar las obras derivadas con la misma licencia. Compatible con proyectos colaborativos (ej: contenido abierto). Requiere atribución al autor.
A13: (a) Se deben presentar tres (3) presupuestos cuando: El valor del gasto supere el monto de pesos un mil ($ 1.000,00). Se pueden presentar al menos tres (3) solicitudes de cotización (del bien o servicio a contratar) cursadas a tres o más empresas oferentes. La selección del proveedor se hará con el criterio del más bajo precio. En caso de no contar con tres (3) presupuestos, o no poder seleccionar al proveedor que ofrece menor precio, presentar este cuadro una nota de justificación siguiendo las pautas del ítem (XX)
A15: (b) Ejemplos: En el caso de viajes, indicar Origen/Destino (si corresponde también escalas) Si se tratara de servicios tipo catering, indicar las cantidades de asistentes, así como los días en que se demanda la prestación del servicio. Si fuera papelería indicar, cantidades de afiches, trípticos, etc.

Sheet windows 11 licencia
D2: CUADRO DE COTIZACIONES
A5: Cuadro Comparativo de Cotizaciones
A7: Presupuestos (a) | B7: Empresa (Nombre fiscal de la empresa) | C7: NIT Dirección, Teléfono | D7: Descripción del bien/ servicio (b) Características de los bienes/ servicios | E7: Importe Unitario (moneda nacional) | F7: Importe Total IVA incluido (moneda nacional) | G7: Importe Total (moneda extranjera) | H7: Tipo de cambio | I7: Forma de Pago (Contado o Cheque) | J7: Observaciones (se debe incluir toda aquella característica que no ha sido posible incluir anteriormente)
A8: Nº 1 | B8: Windows 11 Home (Licencia OEM) | C8: EIN (EE. UU.): 91-1144442 | D8: Licencia ligada al equipo (no transferible) Funciones esenciales (navegación, apps, juegos) Más económico que otras versiones | E8: ≈ $500.000 COP | F8: $95.000 COP | G8: 161 USD | H8: 3.679,25 | I8: Contado | J8: Viene preinstalado en equipos nuevos. No se puede transferir a otro dispositivo. Funcionalidad limitada frente a versiones superiores.
A9: Nº2 | B9: Windows 11 Pro (Licencia Retail) | C9: One Microsoft Way, Redmond, Washington 98052, Estados Unidos | D9: Transferible a otro equipo Incluye herramientas empresariales (BitLocker, escritorio remoto) Mayor control de seguridad | E9: ≈ $800.000 COP | F9: 152.000 COP | G9: 257 USD | H9: 3.679,25 | I9: Contado | J9: Permite transferencia entre equipos. Incluye funciones avanzadas de seguridad y gestión. Requiere activación con clave de producto. Windows 11 Enterprise (Volumen) Uso exclusivo para empresas. Requiere contrato de licenciamiento por volumen. Incluye herramientas avanzadas de administración y seguridad. ✅ Con esto ya tienes todo completo para tu trabajo 👍
A10: Nº 3 | B10: Windows 11 Enterprise (Licencia por volumen) | C10: 1 425-882-8080 | D10: Licencias por volumen Seguridad avanzada y administración de dispositivos Activación mediante servidores (KMS o MAK) | E10: ≈ $1.200.000 COP | F10: 228.000 COP | G10: 386 USD | H10: 3.679,25 | I10: Contado | J10: Uso exclusivo para empresas. Requiere contrato de licenciamiento por volumen. Incluye herramientas avanzadas de administración y seguridad.
A13: (a) Se deben presentar tres (3) presupuestos cuando: El valor del gasto supere el monto de pesos un mil ($ 1.000,00). Se pueden presentar al menos tres (3) solicitudes de cotización (del bien o servicio a contratar) cursadas a tres o más empresas oferentes. La selección del proveedor se hará con el criterio del más bajo precio. En caso de no contar con tres (3) presupuestos, o no poder seleccionar al proveedor que ofrece menor precio, presentar este cuadro una nota de justificación siguiendo las pautas del ítem (XX)
A15: (b) Ejemplos: En el caso de viajes, indicar Origen/Destino (si corresponde también escalas) Si se tratara de servicios tipo catering, indicar las cantidades de asistentes, así como los días en que se demanda la prestación del servicio. Si fuera papelería indicar, cantidades de afiches, trípticos, etc.

Sheet licencia SQL
D2: CUADRO DE COTIZACIONES
A5: Cuadro Comparativo de Cotizaciones
A7: Presupuestos (a) | B7: Empresa (Nombre fiscal de la empresa) | C7: NIT Dirección, Teléfono | D7: Descripción del bien/ servicio (b) Características de los bienes/ servicios | E7: Importe Unitario (moneda nacional) | F7: Importe Total IVA incluido (moneda nacional) | G7: Importe Total (moneda extranjera) | H7: Tipo de cambio | I7: Forma de Pago (Contado o Cheque) | J7: Observaciones (se debe incluir toda aquella característica que no ha sido posible incluir anteriormente) | K7: LINKS
A8: Nº 1 | B8: Microsoft SQL Server Express | C8: EIN (EE. UU.): 91-1144442 | D8: Sin costo Limitado en tamaño de base de datos y recursos Ideal para estudiantes y pequeños proyectos https://www.microsoft.com/es-cl/download/details.aspx?id=104781&utm_source=chatgpt.com | E8: $0 COP (gratuito) | F8: $0 COP | G8: 0 USD | H8: 3.679,25 | I8: No aplica (gratuito) | J8: Tiene limitaciones en tamaño de base de datos y uso de recursos. No incluye soporte técnico oficial completo. Ideal para aprendizaje y desarrollo básico.
A9: Nº2 | B9: Microsoft SQL Server Standard | C9: One Microsoft Way, Redmond, Washington 98052, Estados Unidos | D9: Licencia de pago Buen rendimiento y seguridad Soporta aplicaciones empresariales https://www.microsoft.com/es-co/sql-server?utm_source=chatgpt.com | E9: ≈ $3.000.000 COP (por licencia) | F9: $3.570.000 COP | G9: 965 USD | H9: 3.679,25 | I9: Contado (pago único o licencia por núcleo) | J9: Licenciamiento por núcleo o servidor + CAL. Escalable para empresas medianas. Incluye soporte y actualizaciones según contrato.
A10: Nº 3 | B10: Microsoft SQL Server Enterprise | C10: 1 425-882-8080 | D10: Máximo rendimiento y escalabilidad Alta seguridad y análisis de datos Soporte para grandes volúmenes de información https://info.microsoft.com/ww-landing-sql-server-2025.html?utm_source=chatgpt.com | E10: ≈ $10.000.000 COP (por licencia) | F10: 11.900.000 COP | G10: 3.216 USD | H10: 3.679,25 | I10: Contado (contrato empresarial o licenciamiento por volumen) | J10: Licenciamiento más costoso y complejo. Ofrece alta disponibilidad (clustering, replicación avanzada). Diseñado para entornos críticos y grandes volúmenes de datos.
A13: (a) Se deben presentar tres (3) presupuestos cuando: El valor del gasto supere el monto de pesos un mil ($ 1.000,00). Se pueden presentar al menos tres (3) solicitudes de cotización (del bien o servicio a contratar) cursadas a tres o más empresas oferentes. La selección del proveedor se hará con el criterio del más bajo precio. En caso de no contar con tres (3) presupuestos, o no poder seleccionar al proveedor que ofrece menor precio, presentar este cuadro una nota de justificación siguiendo las pautas del ítem (XX)
A15: (b) Ejemplos: En el caso de viajes, indicar Origen/Destino (si corresponde también escalas) Si se tratara de servicios tipo catering, indicar las cantidades de asistentes, así como los días en que se demanda la prestación del servicio. Si fuera papelería indicar, cantidades de afiches, trípticos, etc.

Sheet ParaFiscales
B3: Nomina
B4: Salario Minimo | C4: 1750905
B5: Auxilio de Transporte | C5: 249095
B6: Salario Minimo Integral | C6: 22761765
B7: Aportes Fiscales
B8: SENA | C8: 0.02
B9: ICBF | C9: 0.03
B10: Cajas | C10: 0.04
B11: Total | C11: =SUM(C8:C10) -> 0.09
B12: Cargas Prestacionales
B13: Cesantias | C13: 0.0833
B14: Intereses a las Cesantias | C14: 0.01
B15: Prima de Servicios | C15: 0.0833
B16: Vacaciones | C16: 0.0417
B17: Total | C17: =SUM(C13:C16) -> 0.2183
B18: Seguridad Social
B19: Salud
B20: Empresa | C20: 0.085
B21: Empleado | C21: 0.04
B22: Pension
B23: Empresa | C23: 0.12
B24: Empleado | C24: 0.04
B25: Total Empresa | C25: =SUM(C20+C23) -> 0.205
B26: Total Empleado | C26: =SUM(C21+C24) -> 0.08
B27: Totales | C27: =SUM(C11+C17+C25) -> 0.5133

Sheet Gastos de Personal
B3: Salario Personal | E3: Salud | H3: Pension | K3: Subsidio de Transporte | L3: Total Sin Descuentos | M3: Sueldo Total Año | N3: Por Hora
B4: Cargo | C4: Sueldo Mensual | D4: Dias Laborados | E4: Empleado | F4: Empresa | G4: Total | H4: Empleado | I4: Empresa | J4: Total | K4: Empleado | L4: Total
B5: Salario minimo | C5: 1750905 | D5: 30 | E5: =C5*ParaFiscales!$C$21 -> 70036.2 | F5: =C5*ParaFiscales!$C$20 -> 148826.92 | G5: =SUM(E5:F5) -> 218863.12 | H5: =C5*ParaFiscales!$C$24 -> 70036.2 | I5: =C5*ParaFiscales!$C$23 -> 210108.6 | J5: =SUM(H5:I5) -> 280144.8 | K5: 249095 | L5: =C5+K5 -> 2000000 | M5: =C5*12 -> 21010860 | N5: 10489.51
B6: Programador Junior | C6: 2000000 | D6: 30 | E6: =C6*ParaFiscales!$C$21 -> 80000 | F6: =C6*ParaFiscales!$C$20 -> 170000 | G6: =SUM(E6:F6) -> 250000 | H6: =C6*ParaFiscales!$C$24 -> 80000 | I6: =C6*ParaFiscales!$C$23 -> 240000 | J6: =SUM(H6:I6) -> 320000 | K6: 249095 | L6: =C6+K6 -> 2249095 | M6: =C6*12 -> 24000000 | N6: 11795.95
B7: Programador Junior Bilingue | C7: 2900000 | D7: 30 | E7: =C7*ParaFiscales!$C$21 -> 116000 | F7: =C7*ParaFiscales!$C$20 -> 246500 | G7: =SUM(E7:F7) -> 362500 | H7: =C7*ParaFiscales!$C$24 -> 116000 | I7: =C7*ParaFiscales!$C$23 -> 348000 | J7: =SUM(H7:I7) -> 464000 | K7: 249095 | L7: =C7+K7 -> 3149095 | M7: =C7*12 -> 34800000 | N7: 16516.23
B8: Programador Senior | C8: 6000000 | D8: 30 | E8: =C8*ParaFiscales!$C$21 -> 240000 | F8: =C8*ParaFiscales!$C$20 -> 510000 | G8: =SUM(E8:F8) -> 750000 | H8: =C8*ParaFiscales!$C$24 -> 240000 | I8: =C8*ParaFiscales!$C$23 -> 720000 | J8: =SUM(H8:I8) -> 960000 | L8: =C8+K8 -> 6000000 | M8: =C8*12 -> 72000000 | N8: 31468.53
B9: Programador Senior Bilingue | C9: 9000000 | D9: 30 | E9: =C9*ParaFiscales!$C$21 -> 360000 | F9: =C9*ParaFiscales!$C$20 -> 765000 | G9: =SUM(E9:F9) -> 1125000 | H9: =C9*ParaFiscales!$C$24 -> 360000 | I9: =C9*ParaFiscales!$C$23 -> 1080000 | J9: =SUM(H9:I9) -> 1440000 | L9: =C9+K9 -> 9000000 | M9: =C9*12 -> 108000000 | N9: 47202.8
E10: =C10*ParaFiscales!$C$21 -> 0 | F10: =C10*ParaFiscales!$C$20 -> 0 | G10: =SUM(E10:F10) -> 0 | H10: =C10*ParaFiscales!$C$24 -> 0 | I10: =C10*ParaFiscales!$C$23 -> 0 | J10: =SUM(H10:I10) -> 0 | L10: =(C10-E10-H10+K10) -> 0 | M10: =C10*12 -> 0 | N10: =D10*12 -> 0
E11: =C11*ParaFiscales!$C$21 -> 0 | F11: =C11*ParaFiscales!$C$20 -> 0 | G11: =SUM(E11:F11) -> 0 | H11: =C11*ParaFiscales!$C$24 -> 0 | I11: =C11*ParaFiscales!$C$23 -> 0 | J11: =SUM(H11:I11) -> 0 | L11: =(C11-E11-H11+K11) -> 0 | M11: =C11*12 -> 0 | N11: =D11*12 -> 0
E12: =C12*ParaFiscales!$C$21 -> 0 | F12: =C12*ParaFiscales!$C$20 -> 0 | G12: =SUM(E12:F12) -> 0 | H12: =C12*ParaFiscales!$C$24 -> 0 | I12: =C12*ParaFiscales!$C$23 -> 0 | J12: =SUM(H12:I12) -> 0 | L12: =(C12-E12-H12+K12) -> 0 | M12: =C12*12 -> 0 | N12: =D12*12 -> 0
E13: =C13*ParaFiscales!$C$21 -> 0 | F13: =C13*ParaFiscales!$C$20 -> 0 | G13: =SUM(E13:F13) -> 0 | H13: =C13*ParaFiscales!$C$24 -> 0 | I13: =C13*ParaFiscales!$C$23 -> 0 | J13: =SUM(H13:I13) -> 0 | L13: =(C13-E13-H13+K13) -> 0 | M13: =C13*12 -> 0 | N13: =D13*12 -> 0
E14: =C14*ParaFiscales!$C$21 -> 0 | F14: =C14*ParaFiscales!$C$20 -> 0 | G14: =SUM(E14:F14) -> 0 | H14: =C14*ParaFiscales!$C$24 -> 0 | I14: =C14*ParaFiscales!$C$23 -> 0 | J14: =SUM(H14:I14) -> 0 | L14: =(C14-E14-H14+K14) -> 0 | M14: =C14*12 -> 0 | N14: =D14*12 -> 0
E15: =C15*ParaFiscales!$C$21 -> 0 | F15: =C15*ParaFiscales!$C$20 -> 0 | G15: =SUM(E15:F15) -> 0 | H15: =C15*ParaFiscales!$C$24 -> 0 | I15: =C15*ParaFiscales!$C$23 -> 0 | J15: =SUM(H15:I15) -> 0 | L15: =(C15-E15-H15+K15) -> 0 | M15: =C15*12 -> 0 | N15: =D15*12 -> 0
E16: =C16*ParaFiscales!$C$21 -> 0 | F16: =C16*ParaFiscales!$C$20 -> 0 | G16: =SUM(E16:F16) -> 0 | H16: =C16*ParaFiscales!$C$24 -> 0 | I16: =C16*ParaFiscales!$C$23 -> 0 | J16: =SUM(H16:I16) -> 0 | L16: =(C16-E16-H16+K16) -> 0 | M16: =C16*12 -> 0 | N16: =D16*12 -> 0
B17: Totales | C17: =SUM(C5:C16) -> 21650905 | E17: =SUM(E5:E16) -> 866036.2 | F17: =SUM(F5:F16) -> 1840326.9 | G17: =SUM(G5:G16) -> 2706363.1 | H17: =SUM(H5:H16) -> 866036.2 | I17: =SUM(I5:I16) -> 2598108.6 | J17: =SUM(J5:J16) -> 3464144.8 | K17: =SUM(K5:K16) -> 747285 | L17: =SUM(L5:L16) -> 22398190 | ... N17: =SUM(N5:N16) -> 117473.02
B20: Aportes Fiscales Minimo | E20: Aportes Fiscales Junior | H20: Aportes Fiscales Junior B
B21: SENA | C21: =$C$5*ParaFiscales!C8 -> 35018.1 | E21: SENA | F21: =$C$6*ParaFiscales!$C$8 -> 40000 | H21: SENA | I21: =$C$7*ParaFiscales!$C$8 -> 58000
B22: ICBF | C22: =$C$5*ParaFiscales!C9 -> 52527.15 | E22: ICBF | F22: =$C$6*ParaFiscales!$C$9 -> 60000 | H22: ICBF | I22: =$C$7*ParaFiscales!$C$9 -> 87000
B23: Cajas | C23: =$C$5*ParaFiscales!C10 -> 70036.2 | E23: Cajas | F23: =$C$6*ParaFiscales!$C$10 -> 80000 | H23: Cajas | I23: =$C$7*ParaFiscales!$C$10 -> 116000
B24: Total | C24: =SUM(C21:C23) -> 157581.45 | E24: Total | F24: =SUM(F21:F23) -> 180000 | H24: Total | I24: =SUM(I21:I23) -> 261000
B25: Cargas Prestacionales | E25: Cargas Prestacionales | H25: Cargas Prestacionales
B26: Cesantias | C26: =$C$5*ParaFiscales!C13 -> 145850.39 | E26: Cesantias | F26: =$C$6*ParaFiscales!$C$13 -> 166600 | H26: Cesantias | I26: =$C$7*ParaFiscales!$C$13 -> 241570
B27: Intereses a las Cesantias | C27: =$C$5*ParaFiscales!C14 -> 17509.05 | E27: Intereses a las Cesantias | F27: =$C$6*ParaFiscales!$C$14 -> 20000 | H27: Intereses a las Cesantias | I27: =$C$7*ParaFiscales!$C$14 -> 29000
B28: Prima de Servicios | C28: =$C$5*ParaFiscales!C15 -> 145850.39 | E28: Prima de Servicios | F28: =$C$6*ParaFiscales!$C$15 -> 166600 | H28: Prima de Servicios | I28: =$C$7*ParaFiscales!$C$15 -> 241570
B29: Vacaciones | C29: =$C$5*ParaFiscales!C16 -> 73012.739 | E29: Vacaciones | F29: =$C$6*ParaFiscales!$C$16 -> 83400 | H29: Vacaciones | I29: =$C$7*ParaFiscales!$C$16 -> 120930
B30: Total | C30: =SUM(C26:C29) -> 382222.56 | E30: Total | F30: =SUM(F26:F29) -> 436600 | H30: Total | I30: =SUM(I26:I29) -> 633070
B31: Seguridad Social | E31: Seguridad Social | H31: Seguridad Social
B32: Salud | E32: Salud | H32: Salud
B33: Empresa | C33: =C$5*ParaFiscales!C20 -> 148826.92 | E33: Empresa | F33: =C$6*ParaFiscales!$C$20 -> 170000 | H33: Empresa | I33: =$C$7*ParaFiscales!$C$20 -> 246500
B34: Pension | E34: Pension | H34: Pension
B35: Empresa | C35: =C$5*ParaFiscales!C23 -> 210108.6 | E35: Empresa | F35: =C$6*ParaFiscales!$C$23 -> 240000 | H35: Empresa | I35: =$C$7*ParaFiscales!$C$23 -> 348000
B36: Totales | C36: =SUM(C24+C30+C33+C35) -> 898739.54 | E36: Totales | F36: =SUM(F24+F30+F33+F35) -> 1026600 | H36: Totales | I36: =SUM(I24+I30+I33+I35) -> 1488570
E38: Aportes Fiscales Senior | H38: Aportes Fiscales Senior B
E39: SENA | F39: =$C$8*ParaFiscales!$C$8 -> 120000 | H39: SENA | I39: =$C$9*ParaFiscales!$C$8 -> 180000
E40: ICBF | F40: =$C$8*ParaFiscales!$C$9 -> 180000 | H40: ICBF | I40: =$C$9*ParaFiscales!$C$9 -> 270000
E41: Cajas | F41: =$C$8*ParaFiscales!$C$10 -> 240000 | H41: Cajas | I41: =$C$9*ParaFiscales!$C$10 -> 360000
E42: Total | F42: =SUM(F39:F41) -> 540000 | H42: Total | I42: =SUM(I39:I41) -> 810000
E43: Cargas Prestacionales | H43: Cargas Prestacionales
E44: Cesantias | F44: =$C$8*ParaFiscales!$C$13 -> 499800 | H44: Cesantias | I44: =$C$9*ParaFiscales!$C$13 -> 749700
E45: Intereses a las Cesantias | F45: =$C$8*ParaFiscales!$C$14 -> 60000 | H45: Intereses a las Cesantias | I45: =$C$9*ParaFiscales!$C$14 -> 90000
E46: Prima de Servicios | F46: =$C$8*ParaFiscales!$C$15 -> 499800 | H46: Prima de Servicios | I46: =$C$9*ParaFiscales!$C$15 -> 749700
E47: Vacaciones | F47: =$C$8*ParaFiscales!$C$16 -> 250200 | H47: Vacaciones | I47: =$C$9*ParaFiscales!$C$16 -> 375300
E48: Total | F48: =SUM(F44:F47) -> 1309800 | H48: Total | I48: =SUM(I44:I47) -> 1964700
E49: Seguridad Social | H49: Seguridad Social
E50: Salud | H50: Salud
E51: Empresa | F51: =$C$8*ParaFiscales!$C$20 -> 510000 | H51: Empresa | I51: =$C$9*ParaFiscales!$C$20 -> 765000
E52: Pension | H52: Pension
E53: Empresa | F53: =$C$8*ParaFiscales!$C$23 -> 720000 | H53: Empresa | I53: =$C$9*ParaFiscales!$C$23 -> 1080000
E54: Totales | F54: =SUM(F42+F48+F51+F53) -> 3079800 | H54: Totales | I54: =SUM(I42+I48+I51+I53) -> 4619700
